{
  "schema_version": "1.0",
  "corpus": "Rockwool International, 31 transcripts",
  "total_claims": 47,
  "claims": [
    {
      "claim_id": "RKW-001",
      "thread_id": "T-production-ramp-up",
      "source_doc": "00_2021-05-20_earnings_call_Q1",
      "source_section": "mgmt_discussion",
      "date_made": "2021-05-20",
      "speaker": "Jens Birgersson",
      "quote": "we got quite busy with ramping up shifts – adding shifts, getting people back in on the production lines.",
      "paraphrase": "Rockwool is ramping up production by adding shifts and bringing back employees to production lines.",
      "category": "operational",
      "subject": "Production ramp-up",
      "timeframe": "short-term",
      "target_value": "N/A",
      "hedge_level": "firm",
      "falsifiable": "Y",
      "notes": null
    },
    {
      "claim_id": "RKW-002",
      "thread_id": "T-west-virginia-factory-startup",
      "source_doc": "00_2021-05-20_earnings_call_Q1",
      "source_section": "mgmt_discussion",
      "date_made": "2021-05-20",
      "speaker": "Jens Birgersson",
      "quote": "midyear early third quarter, we should be starting to produce there.",
      "paraphrase": "Rockwool expects to start production at the new factory in West Virginia by midyear or early third quarter 2021.",
      "category": "capex_capacity",
      "subject": "West Virginia factory startup",
      "timeframe": "mid-2021",
      "target_value": "midyear early third quarter 2021",
      "hedge_level": "firm",
      "falsifiable": "Y",
      "notes": null
    },
    {
      "claim_id": "RKW-003",
      "thread_id": "T-fy2021-financial-guidance",
      "source_doc": "00_2021-05-20_earnings_call_Q1",
      "source_section": "mgmt_discussion",
      "date_made": "2021-05-20",
      "speaker": "Jens Birgersson",
      "quote": "double digit top line 10% to 12%, EBIT margin around 12%, and the investment level around €730 million.",
      "paraphrase": "Rockwool maintains its guidance for 2021 with a top line growth of 10% to 12%, EBIT margin around 12%, and investment level around €730 million.",
      "category": "financial_guidance",
      "subject": "FY2021 financial guidance",
      "timeframe": "FY2021",
      "target_value": "10% to 12%, ~€730 million",
      "hedge_level": "firm",
      "falsifiable": "Y",
      "notes": null
    },
    {
      "claim_id": "RKW-004",
      "thread_id": "T-fy2021-financial-guidance",
      "source_doc": "00_2021-05-20_earnings_call_Q1",
      "source_section": "qa",
      "date_made": "2021-05-20",
      "speaker": "Jens Birgersson",
      "quote": "I definitely see that we should be able to grow 10% to 12%.",
      "paraphrase": "Rockwool expects to achieve a growth rate of 10% to 12% in 2021.",
      "category": "market_outlook",
      "subject": "FY2021 revenue growth",
      "timeframe": "FY2021",
      "target_value": "10% to 12%",
      "hedge_level": "firm",
      "falsifiable": "Y",
      "notes": null
    },
    {
      "claim_id": "RKW-005",
      "thread_id": "T-market-outlook",
      "source_doc": "00_2021-05-20_earnings_call_Q1",
      "source_section": "qa",
      "date_made": "2021-05-20",
      "speaker": "Jens Birgersson",
      "quote": "we could be relatively sure that we have 18 to 24 months of good business, good economic cycle.",
      "paraphrase": "Rockwool anticipates 18 to 24 months of favorable business conditions and economic cycle.",
      "category": "market_outlook",
      "subject": "Market outlook",
      "timeframe": "18 to 24 months",
      "target_value": "18 to 24 months",
      "hedge_level": "soft",
      "falsifiable": "partial",
      "notes": null
    },
    {
      "claim_id": "RKW-006",
      "thread_id": "T-capex-guidance",
      "source_doc": "00_2021-05-20_earnings_call_Q1",
      "source_section": "qa",
      "date_made": "2021-05-20",
      "speaker": "Jens Birgersson",
      "quote": "we will have further discussions on that. That combined with fuel transition over the next 10 years to meet our science-based target, that means we are probably more geared to staying on CapEx level that is not – you're not going to see €200 million from us.",
      "paraphrase": "Rockwool plans to maintain a capital expenditure level above €200 million to support growth and fuel transition over the next 10 years.",
      "category": "capex_capacity",
      "subject": "CapEx guidance",
      "timeframe": "next 10 years",
      "target_value": "above €200 million",
      "hedge_level": "firm",
      "falsifiable": "Y",
      "notes": null
    },
    {
      "claim_id": "RKW-007",
      "thread_id": "T-construction-industry-outlook",
      "source_doc": "00_2021-05-20_earnings_call_Q1",
      "source_section": "qa",
      "date_made": "2021-05-20",
      "speaker": "Jens Birgersson",
      "quote": "I think we will see a busy construction industry. I think we will see money going into renovation.",
      "paraphrase": "Rockwool expects a busy construction industry with increased investment in renovation.",
      "category": "market_outlook",
      "subject": "Construction industry outlook",
      "timeframe": "short-term",
      "target_value": "N/A",
      "hedge_level": "soft",
      "falsifiable": "N",
      "notes": null
    },
    {
      "claim_id": "RKW-008",
      "thread_id": "T-fy2021-financial-guidance",
      "source_doc": "00_2021-05-20_earnings_call_Q1",
      "source_section": "qa",
      "date_made": "2021-05-20",
      "speaker": "Jens Birgersson",
      "quote": "we should deliver the full-year guidance and you might see a quarter that is really, really good and some maybe a little bit lower or you don't see the end of those quarters.",
      "paraphrase": "Rockwool expects to deliver its full-year guidance despite potential quarterly fluctuations in performance.",
      "category": "financial_guidance",
      "subject": "FY2021 financial guidance",
      "timeframe": "FY2021",
      "target_value": "N/A",
      "hedge_level": "soft",
      "falsifiable": "N",
      "notes": null
    },
    {
      "claim_id": "RKW-009",
      "thread_id": "T-2021-performance-outlook",
      "source_doc": "00_2021-05-20_earnings_call_Q1",
      "source_section": "qa",
      "date_made": "2021-05-20",
      "speaker": "Jens Birgersson",
      "quote": "we have the stimuli. We're all going to get vaccines. I feel comfortable that 2021 is a better year than 2019.",
      "paraphrase": "Rockwool is confident that 2021 will outperform 2019 due to economic stimuli and vaccination progress.",
      "category": "market_outlook",
      "subject": "2021 performance outlook",
      "timeframe": "2021",
      "target_value": "better than 2019",
      "hedge_level": "soft",
      "falsifiable": "N",
      "notes": null
    },
    {
      "claim_id": "RKW-010",
      "thread_id": "T-t-west-virginia-factory-startup",
      "source_doc": "01_2021-06-08_esg_meeting",
      "source_section": "mgmt_discussion",
      "date_made": "2021-06-08",
      "speaker": "Mirella Vitale",
      "quote": "the West Virginia facility has begun its running process in May, and we expect to be – begin all our commercial operations during the end of this month by late June.",
      "paraphrase": "ROCKWOOL expects to begin all commercial operations at the West Virginia facility by late June 2021.",
      "category": "operational",
      "subject": "T-west-virginia-factory-startup",
      "timeframe": "June 2021",
      "target_value": "late June 2021",
      "hedge_level": "firm",
      "falsifiable": "Y",
      "notes": null
    },
    {
      "claim_id": "RKW-011",
      "thread_id": "T-t-2021-performance-outlook",
      "source_doc": "01_2021-06-08_esg_meeting",
      "source_section": "mgmt_discussion",
      "date_made": "2021-06-08",
      "speaker": "Anthony Abbotts",
      "quote": "we expect by the end of the year to be up around 15% or even more compared to the 35% that we need to achieve by end of 2022.",
      "paraphrase": "ROCKWOOL expects to achieve around 15% energy efficiency renovation by the end of 2021, compared to the 35% target for the end of 2022.",
      "category": "sustainability",
      "subject": "T-2021-performance-outlook",
      "timeframe": "end of 2021",
      "target_value": "15%",
      "hedge_level": "soft",
      "falsifiable": "partial",
      "notes": null
    },
    {
      "claim_id": "RKW-012",
      "thread_id": "T-t-capex-guidance",
      "source_doc": "01_2021-06-08_esg_meeting",
      "source_section": "mgmt_discussion",
      "date_made": "2021-06-08",
      "speaker": "Anthony Abbotts",
      "quote": "we've saved around €4 million of CapEx.",
      "paraphrase": "ROCKWOOL has saved approximately €4 million in CapEx through the renovation of its office in Gladbach.",
      "category": "financial_guidance",
      "subject": "T-capex-guidance",
      "timeframe": "N/A",
      "target_value": "€4 million",
      "hedge_level": "firm",
      "falsifiable": "Y",
      "notes": null
    },
    {
      "claim_id": "RKW-013",
      "thread_id": "T-t-construction-industry-outlook",
      "source_doc": "01_2021-06-08_esg_meeting",
      "source_section": "mgmt_discussion",
      "date_made": "2021-06-08",
      "speaker": "Anthony Abbotts",
      "quote": "we've avoided 2,500 tonnes of construction waste going to landfill, and we've avoided going to landfill.",
      "paraphrase": "ROCKWOOL has avoided 2,500 tonnes of construction waste going to landfill through its renovation project.",
      "category": "sustainability",
      "subject": "T-construction-industry-outlook",
      "timeframe": "N/A",
      "target_value": "2,500 tonnes",
      "hedge_level": "firm",
      "falsifiable": "Y",
      "notes": null
    },
    {
      "claim_id": "RKW-014",
      "thread_id": "T-t-construction-industry-outlook",
      "source_doc": "01_2021-06-08_esg_meeting",
      "source_section": "mgmt_discussion",
      "date_made": "2021-06-08",
      "speaker": "Anthony Abbotts",
      "quote": "we've avoided 1,800 tons of CO2 associated with the production of new construction materials if you had done a new build.",
      "paraphrase": "ROCKWOOL has avoided 1,800 tons of CO2 emissions through its renovation project compared to a new build.",
      "category": "sustainability",
      "subject": "T-construction-industry-outlook",
      "timeframe": "N/A",
      "target_value": "1,800 tons",
      "hedge_level": "firm",
      "falsifiable": "Y",
      "notes": null
    },
    {
      "claim_id": "RKW-015",
      "thread_id": "T-t-construction-industry-outlook",
      "source_doc": "01_2021-06-08_esg_meeting",
      "source_section": "mgmt_discussion",
      "date_made": "2021-06-08",
      "speaker": "Anthony Abbotts",
      "quote": "we have been using our reclaimed waste service rock cycle during the renovation project.",
      "paraphrase": "ROCKWOOL has utilized its reclaimed waste service, Rock Cycle, during the renovation project.",
      "category": "sustainability",
      "subject": "T-construction-industry-outlook",
      "timeframe": "N/A",
      "target_value": "N/A",
      "hedge_level": "firm",
      "falsifiable": "Y",
      "notes": null
    },
    {
      "claim_id": "RKW-016",
      "thread_id": "T-t-construction-industry-outlook",
      "source_doc": "01_2021-06-08_esg_meeting",
      "source_section": "mgmt_discussion",
      "date_made": "2021-06-08",
      "speaker": "Anthony Abbotts",
      "quote": "we have achieved the DGNB gold certification, which is extremely difficult to attain for renovation.",
      "paraphrase": "ROCKWOOL has achieved the DGNB gold certification for its renovation project, which is difficult to attain.",
      "category": "sustainability",
      "subject": "T-construction-industry-outlook",
      "timeframe": "N/A",
      "target_value": "DGNB gold certification",
      "hedge_level": "firm",
      "falsifiable": "Y",
      "notes": null
    },
    {
      "claim_id": "RKW-017",
      "thread_id": "T-pricing-outlook",
      "source_doc": "02_2021-08-19_earnings_call_Q2",
      "source_section": "qa",
      "date_made": "2021-08-19",
      "speaker": "Jens Birgersson",
      "quote": "I foresee that the beginning of the second half-year, pricing will improve gradually.",
      "paraphrase": "Pricing is expected to improve gradually at the beginning of the second half of the year.",
      "category": "financial_guidance",
      "subject": "Pricing outlook",
      "timeframe": "H2 2021",
      "target_value": "gradually improve",
      "hedge_level": "soft",
      "falsifiable": "partial",
      "notes": null
    },
    {
      "claim_id": "RKW-018",
      "thread_id": "T-pricing-outlook",
      "source_doc": "02_2021-08-19_earnings_call_Q2",
      "source_section": "qa",
      "date_made": "2021-08-19",
      "speaker": "Jens Birgersson",
      "quote": "And then, when we get to Q4, we're going to be in balance between inflation and price.",
      "paraphrase": "By Q4, the company expects to achieve a balance between inflation and pricing.",
      "category": "financial_guidance",
      "subject": "Pricing outlook",
      "timeframe": "Q4 2021",
      "target_value": "balance between inflation and price",
      "hedge_level": "soft",
      "falsifiable": "partial",
      "notes": null
    },
    {
      "claim_id": "RKW-019",
      "thread_id": "T-capex-guidance",
      "source_doc": "02_2021-08-19_earnings_call_Q2",
      "source_section": "qa",
      "date_made": "2021-08-19",
      "speaker": "Jens Birgersson",
      "quote": "I would think that on the €370 million, the challenge you have when you go up on full capacity.",
      "paraphrase": "CapEx is expected to be around €370 million, with challenges related to full capacity.",
      "category": "capex_capacity",
      "subject": "CapEx guidance",
      "timeframe": "2021",
      "target_value": "€370 million",
      "hedge_level": "soft",
      "falsifiable": "partial",
      "notes": null
    },
    {
      "claim_id": "RKW-020",
      "thread_id": "T-poland-line-startup",
      "source_doc": "02_2021-08-19_earnings_call_Q2",
      "source_section": "mgmt_discussion",
      "date_made": "2021-08-19",
      "speaker": "Jens Birgersson",
      "quote": "We should start that line up end of first quarter 2022.",
      "paraphrase": "The new line in Poland is expected to start up by the end of Q1 2022.",
      "category": "capex_capacity",
      "subject": "Poland line startup",
      "timeframe": "Q1 2022",
      "target_value": "end of Q1 2022",
      "hedge_level": "firm",
      "falsifiable": "Y",
      "notes": null
    },
    {
      "claim_id": "RKW-021",
      "thread_id": "T-west-virginia-factory-startup",
      "source_doc": "02_2021-08-19_earnings_call_Q2",
      "source_section": "qa",
      "date_made": "2021-08-19",
      "speaker": "Jens Birgersson",
      "quote": "We are not moving as fast as we can to ramp up production. And so far, so good. But it comes at a good time.",
      "paraphrase": "The ramp-up of production at the West Virginia factory is progressing, and it is timely given market conditions.",
      "category": "capex_capacity",
      "subject": "West Virginia factory startup",
      "timeframe": "2021",
      "target_value": "progressing",
      "hedge_level": "soft",
      "falsifiable": "partial",
      "notes": null
    },
    {
      "claim_id": "RKW-022",
      "thread_id": "T-market-outlook",
      "source_doc": "02_2021-08-19_earnings_call_Q2",
      "source_section": "mgmt_discussion",
      "date_made": "2021-08-19",
      "speaker": "Jens Birgersson",
      "quote": "I think there is one important insight when you look at all of these directives, that is only the energy taxation directive that need a unified decision that everyone say yes.",
      "paraphrase": "The energy taxation directive requires a unified decision for implementation, which may affect future business.",
      "category": "market_outlook",
      "subject": "Market outlook",
      "timeframe": "future",
      "target_value": "unified decision needed",
      "hedge_level": "soft",
      "falsifiable": "N",
      "notes": null
    },
    {
      "claim_id": "RKW-023",
      "thread_id": "T-sustainability-progress",
      "source_doc": "02_2021-08-19_earnings_call_Q2",
      "source_section": "mgmt_discussion",
      "date_made": "2021-08-19",
      "speaker": "Jens Birgersson",
      "quote": "We are ahead of the plan.",
      "paraphrase": "The company is ahead of its sustainability plan regarding CO2 emissions.",
      "category": "sustainability",
      "subject": "Sustainability progress",
      "timeframe": "ongoing",
      "target_value": "ahead of plan",
      "hedge_level": "soft",
      "falsifiable": "N",
      "notes": null
    },
    {
      "claim_id": "RKW-024",
      "thread_id": "T-japan-factory-upgrade",
      "source_doc": "02_2021-08-19_earnings_call_Q2",
      "source_section": "mgmt_discussion",
      "date_made": "2021-08-19",
      "speaker": "Jens Birgersson",
      "quote": "We will do that.",
      "paraphrase": "The company commits to upgrading the factory in Japan.",
      "category": "capex_capacity",
      "subject": "Japan factory upgrade",
      "timeframe": "2022",
      "target_value": "upgrade",
      "hedge_level": "firm",
      "falsifiable": "Y",
      "notes": null
    },
    {
      "claim_id": "RKW-025",
      "thread_id": "T-japan-factory-upgrade",
      "source_doc": "02_2021-08-19_earnings_call_Q2",
      "source_section": "mgmt_discussion",
      "date_made": "2021-08-19",
      "speaker": "Jens Birgersson",
      "quote": "We have started that and we have people coming on the ground now to start to plan that one out.",
      "paraphrase": "The company has initiated planning for the factory upgrade in Japan.",
      "category": "capex_capacity",
      "subject": "Japan factory upgrade",
      "timeframe": "2021",
      "target_value": "planning initiated",
      "hedge_level": "firm",
      "falsifiable": "Y",
      "notes": null
    },
    {
      "claim_id": "RKW-026",
      "thread_id": "T-production-ramp-up",
      "source_doc": "02_2021-08-19_earnings_call_Q2",
      "source_section": "qa",
      "date_made": "2021-08-19",
      "speaker": "Jens Birgersson",
      "quote": "We are ramping up. We have certain stock, and there's no need to push sales in a certain segment if that – if you don't have the tonnes around then, that will be a delivery in December.",
      "paraphrase": "The company is ramping up production and managing stock levels to optimize sales.",
      "category": "operational",
      "subject": "Production ramp-up",
      "timeframe": "2021",
      "target_value": "ramping up",
      "hedge_level": "soft",
      "falsifiable": "partial",
      "notes": null
    },
    {
      "claim_id": "RKW-027",
      "thread_id": "T-energy-efficiency-improvement",
      "source_doc": "02_2021-08-19_earnings_call_Q2",
      "source_section": "mgmt_discussion",
      "date_made": "2021-08-19",
      "speaker": "Jens Birgersson",
      "quote": "We will get better after [indiscernible] (00:25:42).",
      "paraphrase": "The company expects to improve energy efficiency in its buildings after completing ongoing projects.",
      "category": "sustainability",
      "subject": "Energy efficiency improvement",
      "timeframe": "future",
      "target_value": "improve",
      "hedge_level": "soft",
      "falsifiable": "N",
      "notes": null
    },
    {
      "claim_id": "RKW-028",
      "thread_id": "T-ebit-margin-outlook",
      "source_doc": "02_2021-08-19_earnings_call_Q2",
      "source_section": "mgmt_discussion",
      "date_made": "2021-08-19",
      "speaker": "Jens Birgersson",
      "quote": "We are happy with that, especially as the mix is a little bit skewed towards -- a bit more flat than we normally do.",
      "paraphrase": "The company is satisfied with the EBIT margin despite a skewed product mix.",
      "category": "financial_guidance",
      "subject": "EBIT margin outlook",
      "timeframe": "2021",
      "target_value": "satisfied",
      "hedge_level": "soft",
      "falsifiable": "N",
      "notes": null
    },
    {
      "claim_id": "RKW-029",
      "thread_id": "T-capacity-utilization",
      "source_doc": "02_2021-08-19_earnings_call_Q2",
      "source_section": "mgmt_discussion",
      "date_made": "2021-08-19",
      "speaker": "Jens Birgersson",
      "quote": "We are ramping up with bringing more ships, go higher up on the capacity utilization.",
      "paraphrase": "The company is increasing capacity utilization to meet rising demand.",
      "category": "operational",
      "subject": "Capacity utilization",
      "timeframe": "2021",
      "target_value": "increasing",
      "hedge_level": "soft",
      "falsifiable": "partial",
      "notes": null
    },
    {
      "claim_id": "RKW-030",
      "thread_id": "T-construction-market-risk",
      "source_doc": "02_2021-08-19_earnings_call_Q2",
      "source_section": "qa",
      "date_made": "2021-08-19",
      "speaker": "Jens Birgersson",
      "quote": "We have a heavy winter, might decide to pause the project for a longer period and then wait for the material to arrive, and then we start off in the New Year.",
      "paraphrase": "There is a risk that construction projects may pause due to material shortages and heavy winter conditions.",
      "category": "market_outlook",
      "subject": "Construction market risk",
      "timeframe": "Q4 2021",
      "target_value": "pause projects",
      "hedge_level": "soft",
      "falsifiable": "partial",
      "notes": null
    },
    {
      "claim_id": "RKW-031",
      "thread_id": "T-capacity-for-growth",
      "source_doc": "02_2021-08-19_earnings_call_Q2",
      "source_section": "qa",
      "date_made": "2021-08-19",
      "speaker": "Jens Birgersson",
      "quote": "We have free capacity so we can grow next year.",
      "paraphrase": "The company has free capacity to support growth in the next year.",
      "category": "capex_capacity",
      "subject": "Capacity for growth",
      "timeframe": "2022",
      "target_value": "free capacity",
      "hedge_level": "firm",
      "falsifiable": "Y",
      "notes": null
    },
    {
      "claim_id": "RKW-032",
      "thread_id": "T-impact-of-ranson-startup",
      "source_doc": "02_2021-08-19_earnings_call_Q2",
      "source_section": "qa",
      "date_made": "2021-08-19",
      "speaker": "Kim Junge Andersen",
      "quote": "We will not quantify specifically, but it's something that is between 0.5 and 1 percentage point.",
      "paraphrase": "The impact of the Ranson factory startup on margins is estimated to be between 0.5 and 1 percentage point.",
      "category": "financial_guidance",
      "subject": "Impact of Ranson startup",
      "timeframe": "H2 2021",
      "target_value": "0.5 to 1 percentage point",
      "hedge_level": "soft",
      "falsifiable": "partial",
      "notes": null
    },
    {
      "claim_id": "RKW-033",
      "thread_id": "T-ebit-margin-outlook",
      "source_doc": "02_2021-08-19_earnings_call_Q2",
      "source_section": "mgmt_discussion",
      "date_made": "2021-08-19",
      "speaker": "Jens Birgersson",
      "quote": "We are happy with that, especially as the mix is a little bit skewed towards -- a bit more flat than we normally do.",
      "paraphrase": "The company is satisfied with the EBIT margin despite a skewed product mix.",
      "category": "financial_guidance",
      "subject": "EBIT margin outlook",
      "timeframe": "2021",
      "target_value": "satisfied",
      "hedge_level": "soft",
      "falsifiable": "N",
      "notes": null
    },
    {
      "claim_id": "RKW-034",
      "thread_id": "T-capacity-utilization",
      "source_doc": "02_2021-08-19_earnings_call_Q2",
      "source_section": "mgmt_discussion",
      "date_made": "2021-08-19",
      "speaker": "Jens Birgersson",
      "quote": "We are ramping up with bringing more ships, go higher up on the capacity utilization.",
      "paraphrase": "The company is increasing capacity utilization to meet rising demand.",
      "category": "operational",
      "subject": "Capacity utilization",
      "timeframe": "2021",
      "target_value": "increasing",
      "hedge_level": "soft",
      "falsifiable": "partial",
      "notes": null
    },
    {
      "claim_id": "RKW-035",
      "thread_id": "T-construction-market-risk",
      "source_doc": "02_2021-08-19_earnings_call_Q2",
      "source_section": "qa",
      "date_made": "2021-08-19",
      "speaker": "Jens Birgersson",
      "quote": "We have a heavy winter, might decide to pause the project for a longer period and then wait for the material to arrive, and then we start off in the New Year.",
      "paraphrase": "There is a risk that construction projects may pause due to material shortages and heavy winter conditions.",
      "category": "market_outlook",
      "subject": "Construction market risk",
      "timeframe": "Q4 2021",
      "target_value": "pause projects",
      "hedge_level": "soft",
      "falsifiable": "partial",
      "notes": null
    },
    {
      "claim_id": "RKW-036",
      "thread_id": "T-capacity-for-growth",
      "source_doc": "02_2021-08-19_earnings_call_Q2",
      "source_section": "qa",
      "date_made": "2021-08-19",
      "speaker": "Jens Birgersson",
      "quote": "We have free capacity so we can grow next year.",
      "paraphrase": "The company has free capacity to support growth in the next year.",
      "category": "capex_capacity",
      "subject": "Capacity for growth",
      "timeframe": "2022",
      "target_value": "free capacity",
      "hedge_level": "firm",
      "falsifiable": "Y",
      "notes": null
    },
    {
      "claim_id": "RKW-037",
      "thread_id": "T-impact-of-ranson-startup",
      "source_doc": "02_2021-08-19_earnings_call_Q2",
      "source_section": "qa",
      "date_made": "2021-08-19",
      "speaker": "Kim Junge Andersen",
      "quote": "We will not quantify specifically, but it's something that is between 0.5 and 1 percentage point.",
      "paraphrase": "The impact of the Ranson factory startup on margins is estimated to be between 0.5 and 1 percentage point.",
      "category": "financial_guidance",
      "subject": "Impact of Ranson startup",
      "timeframe": "H2 2021",
      "target_value": "0.5 to 1 percentage point",
      "hedge_level": "soft",
      "falsifiable": "partial",
      "notes": null
    },
    {
      "claim_id": "RKW-038",
      "thread_id": "T-fy2021-financial-guidance-2",
      "source_doc": "03_2021-11-25_earnings_call_Q3",
      "source_section": "mgmt_discussion",
      "date_made": "2021-11-25",
      "speaker": "Jens Birgersson",
      "quote": "we do not catch up on margin. This is now tighter above 13%",
      "paraphrase": "ROCKWOOL expects the EBIT margin to be above 13%.",
      "category": "financial_guidance",
      "subject": "FY2021 financial guidance",
      "timeframe": "Q4 2021",
      "target_value": "above 13%",
      "hedge_level": "soft",
      "falsifiable": "Y",
      "notes": ""
    },
    {
      "claim_id": "RKW-039",
      "thread_id": "T-t-capex-guidance",
      "source_doc": "03_2021-11-25_earnings_call_Q3",
      "source_section": "mgmt_discussion",
      "date_made": "2021-11-25",
      "speaker": "Jens Birgersson",
      "quote": "the CapEx forecast where we've taken it down a little bit. It doesn't mean that we have on purpose slowed down any capacity investments",
      "paraphrase": "ROCKWOOL has reduced its CapEx guidance to €320 million from €370 million due to a challenging environment.",
      "category": "financial_guidance",
      "subject": "CapEx guidance",
      "timeframe": "2021",
      "target_value": "€320 million",
      "hedge_level": "firm",
      "falsifiable": "Y",
      "notes": ""
    },
    {
      "claim_id": "RKW-040",
      "thread_id": "T-t-construction-industry-outlook",
      "source_doc": "03_2021-11-25_earnings_call_Q3",
      "source_section": "qa",
      "date_made": "2021-11-25",
      "speaker": "Jens Birgersson",
      "quote": "we are building inventory to make sure we have enough seasonal stock for the next high season",
      "paraphrase": "ROCKWOOL is building inventory to prepare for the next high season.",
      "category": "strategic_intent",
      "subject": "construction industry outlook",
      "timeframe": "next high season",
      "target_value": "N/A",
      "hedge_level": "firm",
      "falsifiable": "N",
      "notes": ""
    },
    {
      "claim_id": "RKW-041",
      "thread_id": "T-pricing-outlook-2",
      "source_doc": "03_2021-11-25_earnings_call_Q3",
      "source_section": "qa",
      "date_made": "2021-11-25",
      "speaker": "Jens Birgersson",
      "quote": "we will need a bit of time to normalize this, but it's progressing",
      "paraphrase": "ROCKWOOL expects to normalize gross margins over time, but it will take some time.",
      "category": "market_outlook",
      "subject": "pricing outlook",
      "timeframe": "Q4 2021",
      "target_value": "N/A",
      "hedge_level": "soft",
      "falsifiable": "N",
      "notes": ""
    },
    {
      "claim_id": "RKW-042",
      "thread_id": "T-pricing-outlook-3",
      "source_doc": "03_2021-11-25_earnings_call_Q3",
      "source_section": "qa",
      "date_made": "2021-11-25",
      "speaker": "Jens Birgersson",
      "quote": "we see that we're going to have Q4 where the gross margins are under – we haven't recovered",
      "paraphrase": "ROCKWOOL anticipates that gross margins will remain under pressure in Q4.",
      "category": "market_outlook",
      "subject": "pricing outlook",
      "timeframe": "Q4 2021",
      "target_value": "N/A",
      "hedge_level": "soft",
      "falsifiable": "N",
      "notes": ""
    },
    {
      "claim_id": "RKW-043",
      "thread_id": "T-ebit-margin-outlook-2",
      "source_doc": "03_2021-11-25_earnings_call_Q3",
      "source_section": "qa",
      "date_made": "2021-11-25",
      "speaker": "Jens Birgersson",
      "quote": "we are certainly happy. I mean, we always like more margin but the Systems division also have this",
      "paraphrase": "ROCKWOOL is satisfied with a margin of 14% to 15% for the Systems division.",
      "category": "market_outlook",
      "subject": "EBIT margin outlook",
      "timeframe": "2021",
      "target_value": "14% to 15%",
      "hedge_level": "soft",
      "falsifiable": "Y",
      "notes": ""
    },
    {
      "claim_id": "RKW-044",
      "thread_id": "T-pricing-outlook-4",
      "source_doc": "03_2021-11-25_earnings_call_Q3",
      "source_section": "qa",
      "date_made": "2021-11-25",
      "speaker": "Jens Birgersson",
      "quote": "we are planning and executing on price increases so that we can get contribution margins and gross margins back to where we want them to be on a more normalized level",
      "paraphrase": "ROCKWOOL is planning to execute price increases to restore contribution and gross margins to normalized levels.",
      "category": "market_outlook",
      "subject": "pricing outlook",
      "timeframe": "2022",
      "target_value": "N/A",
      "hedge_level": "firm",
      "falsifiable": "Y",
      "notes": ""
    },
    {
      "claim_id": "RKW-045",
      "thread_id": "T-construction-market-risk-2",
      "source_doc": "03_2021-11-25_earnings_call_Q3",
      "source_section": "qa",
      "date_made": "2021-11-25",
      "speaker": "Jens Birgersson",
      "quote": "we have seen it so many time in Eastern Europe that sometimes it grows a lot, and then we have quarters when it doesn't grow as much",
      "paraphrase": "ROCKWOOL acknowledges that growth in Eastern Europe can fluctuate significantly from quarter to quarter.",
      "category": "market_outlook",
      "subject": "construction market risk",
      "timeframe": "2022",
      "target_value": "N/A",
      "hedge_level": "soft",
      "falsifiable": "N",
      "notes": ""
    },
    {
      "claim_id": "RKW-046",
      "thread_id": "T-market-outlook-2",
      "source_doc": "03_2021-11-25_earnings_call_Q3",
      "source_section": "qa",
      "date_made": "2021-11-25",
      "speaker": "Jens Birgersson",
      "quote": "the high growth areas continues to be North America and Eastern Europe",
      "paraphrase": "ROCKWOOL expects North America and Eastern Europe to remain high growth areas.",
      "category": "market_outlook",
      "subject": "market outlook",
      "timeframe": "2022",
      "target_value": "N/A",
      "hedge_level": "firm",
      "falsifiable": "Y",
      "notes": ""
    },
    {
      "claim_id": "RKW-047",
      "thread_id": "T-t-capex-guidance",
      "source_doc": "03_2021-11-25_earnings_call_Q3",
      "source_section": "qa",
      "date_made": "2021-11-25",
      "speaker": "Kim Junge Andersen",
      "quote": "the investment that we will do over the coming years in Russia for this factory and some other improvements we're making is – will be up to about €200 million",
      "paraphrase": "ROCKWOOL plans to invest up to €200 million in its Russian factory over the coming years.",
      "category": "capex_capacity",
      "subject": "Russia factory investment",
      "timeframe": "2024",
      "target_value": "€200 million",
      "hedge_level": "firm",
      "falsifiable": "Y",
      "notes": ""
    }
  ]
}